src/__init__.py
src/config.py
src/core/extractor.py
src/file_processor.py
src/infra/logger.py
src/infra/logger_stdout.py
src/infra/logger_system.py
src/main.py
src/server.py
keyphrases_mcp-0.0.4.dist-info/WHEEL
keyphrases_mcp-0.0.4.dist-info/entry_points.txt
keyphrases_mcp-0.0.4.dist-info/METADATA
keyphrases_mcp-0.0.4.dist-info/RECORD
