Metadata-Version: 2.3
Name: keyphrases-mcp
Version: 0.0.4
Summary: Keyphrases MCP server - Model Context Protocol server to extract keyphrases from a text using a BERT model
Keywords: keyphrases,keywords,metadata,mcp,model-context-protocol,ai,llm,bert,nlp,text-analysis
Author: Ivan Rublev
Author-email: Ivan Rublev <git@ivanrublev.me>
License: MIT
Classifier: Development Status :: 4 - Beta
Classifier: Intended Audience :: Developers
Classifier: License :: OSI Approved :: MIT License
Classifier: Programming Language :: Python :: 3
Classifier: Programming Language :: Python :: 3.12
Classifier: Topic :: Scientific/Engineering :: Artificial Intelligence
Classifier: Topic :: Text Processing :: Linguistic
Requires-Dist: click>=8.3.0
Requires-Dist: dotenv>=0.9.9
Requires-Dist: fastmcp>=2.12.4
Requires-Dist: keybert[spacy]>=0.9.0
Requires-Dist: keyphrase-vectorizers>=0.0.13
Requires-Dist: numpy>=1.0,<2.0
Requires-Dist: pip>=24.0
Requires-Dist: toml>=0.10.2
Requires-Dist: torch==2.2.2
Requires-Python: >=3.12
